{
  "heroTitle": "Affiliate Pages Built Around Home Appliances and Coffee Gear",
  "heroKicker": "Niche-First Automation Engine",
  "heroDescription": "This site now prioritizes home appliances, kitchen gear, coffee equipment, air treatment, cleaning devices, and home comfort products. A small skincare test bucket exists only to validate engine diversity without taking over the site direction.",
  "featuredReviewSlugs": [
    "coffee-mug-warmer-fastest-heating"
  ],
  "featuredBestSlug": "top-picks",
  "popularComparisonSlugs": [],
  "featuredGuideSlugs": [
    "product-buying-guide",
    "how-to-choose-coffee-gear"
  ],
  "categorySlugs": [
    "coffee"
  ]
}
